{
  "meta": {
    "updated_at": "2026-06-02T22:24:07.248Z",
    "currency": "AED",
    "pegged_to_usd": true
  },
  "nisab": {
    "hanafi": {
      "label": "Hanafi",
      "gold": 45051.27,
      "silver": 5440.17
    },
    "maliki": {
      "label": "Maliki",
      "gold": 45051.27,
      "silver": 5285.94
    },
    "shafii": {
      "label": "Shafi'i",
      "gold": 45051.27,
      "silver": 5285.94
    },
    "hanbali": {
      "label": "Hanbali",
      "gold": 45051.27,
      "silver": 5285.94
    }
  }
}