{
  "meta": {
    "updated_at": "2026-06-04T21:43:49.061Z",
    "currency": "AFN",
    "pegged_to_usd": false
  },
  "nisab": {
    "hanafi": {
      "label": "Hanafi",
      "gold": 763633,
      "silver": 90833
    },
    "maliki": {
      "label": "Maliki",
      "gold": 763633,
      "silver": 88258
    },
    "shafii": {
      "label": "Shafi'i",
      "gold": 763633,
      "silver": 88258
    },
    "hanbali": {
      "label": "Hanbali",
      "gold": 763633,
      "silver": 88258
    }
  }
}