{
  "meta": {
    "updated_at": "2026-06-07T03:34:06.834Z",
    "currency": "AUD",
    "pegged_to_usd": false
  },
  "nisab": {
    "hanafi": {
      "label": "Hanafi",
      "gold": 16799.36,
      "silver": 1896.81
    },
    "maliki": {
      "label": "Maliki",
      "gold": 16799.36,
      "silver": 1843.04
    },
    "shafii": {
      "label": "Shafi'i",
      "gold": 16799.36,
      "silver": 1843.04
    },
    "hanbali": {
      "label": "Hanbali",
      "gold": 16799.36,
      "silver": 1843.04
    }
  }
}