{
  "meta": {
    "updated_at": "2026-05-30T02:46:55.306Z",
    "currency": "BDT",
    "pegged_to_usd": false
  },
  "nisab": {
    "hanafi": {
      "label": "Hanafi",
      "gold": 1519452,
      "silver": 181534
    },
    "maliki": {
      "label": "Maliki",
      "gold": 1519452,
      "silver": 176387
    },
    "shafii": {
      "label": "Shafi'i",
      "gold": 1519452,
      "silver": 176387
    },
    "hanbali": {
      "label": "Hanbali",
      "gold": 1519452,
      "silver": 176387
    }
  }
}