{
  "meta": {
    "updated_at": "2026-07-18T13:11:05.689Z",
    "currency": "BHD",
    "pegged_to_usd": true
  },
  "nisab": {
    "hanafi": {
      "label": "Hanafi",
      "gold": 4128.1,
      "silver": 402.86
    },
    "maliki": {
      "label": "Maliki",
      "gold": 4128.1,
      "silver": 402.86
    },
    "shafii": {
      "label": "Shafi'i",
      "gold": 4128.1,
      "silver": 402.86
    },
    "hanbali": {
      "label": "Hanbali",
      "gold": 4128.1,
      "silver": 402.86
    }
  }
}