{
  "meta": {
    "updated_at": "2026-07-07T17:58:50.209Z",
    "currency": "CAD",
    "pegged_to_usd": false
  },
  "nisab": {
    "hanafi": {
      "label": "Hanafi",
      "gold": 16094.6,
      "silver": 1658.62
    },
    "maliki": {
      "label": "Maliki",
      "gold": 16094.6,
      "silver": 1658.62
    },
    "shafii": {
      "label": "Shafi'i",
      "gold": 16094.6,
      "silver": 1658.62
    },
    "hanbali": {
      "label": "Hanbali",
      "gold": 16094.6,
      "silver": 1658.62
    }
  }
}