{
  "meta": {
    "updated_at": "2026-06-18T22:15:38.809Z",
    "currency": "CAD",
    "pegged_to_usd": false
  },
  "nisab": {
    "hanafi": {
      "label": "Hanafi",
      "gold": 16220.95,
      "silver": 1823.81
    },
    "maliki": {
      "label": "Maliki",
      "gold": 16220.95,
      "silver": 1772.11
    },
    "shafii": {
      "label": "Shafi'i",
      "gold": 16220.95,
      "silver": 1772.11
    },
    "hanbali": {
      "label": "Hanbali",
      "gold": 16220.95,
      "silver": 1772.11
    }
  }
}