{
  "meta": {
    "updated_at": "2026-06-17T15:26:37.824Z",
    "currency": "CAD",
    "pegged_to_usd": false
  },
  "nisab": {
    "hanafi": {
      "label": "Hanafi",
      "gold": 16681.16,
      "silver": 1948.36
    },
    "maliki": {
      "label": "Maliki",
      "gold": 16681.16,
      "silver": 1893.13
    },
    "shafii": {
      "label": "Shafi'i",
      "gold": 16681.16,
      "silver": 1893.13
    },
    "hanbali": {
      "label": "Hanbali",
      "gold": 16681.16,
      "silver": 1893.13
    }
  }
}