{
  "meta": {
    "updated_at": "2026-06-13T10:27:20.861Z",
    "currency": "CHF",
    "pegged_to_usd": false
  },
  "nisab": {
    "hanafi": {
      "label": "Hanafi",
      "gold": 9176.3,
      "silver": 1066.19
    },
    "maliki": {
      "label": "Maliki",
      "gold": 9176.3,
      "silver": 1035.96
    },
    "shafii": {
      "label": "Shafi'i",
      "gold": 9176.3,
      "silver": 1035.96
    },
    "hanbali": {
      "label": "Hanbali",
      "gold": 9176.3,
      "silver": 1035.96
    }
  }
}