{
  "meta": {
    "updated_at": "2026-07-13T17:54:22.089Z",
    "currency": "CHF",
    "pegged_to_usd": false
  },
  "nisab": {
    "hanafi": {
      "label": "Hanafi",
      "gold": 8825.49,
      "silver": 886.86
    },
    "maliki": {
      "label": "Maliki",
      "gold": 8825.49,
      "silver": 886.86
    },
    "shafii": {
      "label": "Shafi'i",
      "gold": 8825.49,
      "silver": 886.86
    },
    "hanbali": {
      "label": "Hanbali",
      "gold": 8825.49,
      "silver": 886.86
    }
  }
}