{
  "meta": {
    "updated_at": "2026-07-20T18:02:29.350Z",
    "currency": "CNY",
    "pegged_to_usd": false
  },
  "nisab": {
    "hanafi": {
      "label": "Hanafi",
      "gold": 74179.92,
      "silver": 7349.87
    },
    "maliki": {
      "label": "Maliki",
      "gold": 74179.92,
      "silver": 7349.87
    },
    "shafii": {
      "label": "Shafi'i",
      "gold": 74179.92,
      "silver": 7349.87
    },
    "hanbali": {
      "label": "Hanbali",
      "gold": 74179.92,
      "silver": 7349.87
    }
  }
}