{
  "meta": {
    "updated_at": "2026-07-05T17:10:16.473Z",
    "currency": "DZD",
    "pegged_to_usd": false
  },
  "nisab": {
    "hanafi": {
      "label": "Hanafi",
      "gold": 1518695.91,
      "silver": 158849.72
    },
    "maliki": {
      "label": "Maliki",
      "gold": 1518695.91,
      "silver": 158849.72
    },
    "shafii": {
      "label": "Shafi'i",
      "gold": 1518695.91,
      "silver": 158849.72
    },
    "hanbali": {
      "label": "Hanbali",
      "gold": 1518695.91,
      "silver": 158849.72
    }
  }
}