{
  "meta": {
    "updated_at": "2026-07-14T17:14:00.541Z",
    "currency": "DZD",
    "pegged_to_usd": false
  },
  "nisab": {
    "hanafi": {
      "label": "Hanafi",
      "gold": 1477484.66,
      "silver": 149581.74
    },
    "maliki": {
      "label": "Maliki",
      "gold": 1477484.66,
      "silver": 149581.74
    },
    "shafii": {
      "label": "Shafi'i",
      "gold": 1477484.66,
      "silver": 149581.74
    },
    "hanbali": {
      "label": "Hanbali",
      "gold": 1477484.66,
      "silver": 149581.74
    }
  }
}