{
  "meta": {
    "updated_at": "2026-06-15T03:55:57.357Z",
    "currency": "EGP",
    "pegged_to_usd": false
  },
  "nisab": {
    "hanafi": {
      "label": "Hanafi",
      "gold": 613268.97,
      "silver": 71857.48
    },
    "maliki": {
      "label": "Maliki",
      "gold": 613268.97,
      "silver": 69820.37
    },
    "shafii": {
      "label": "Shafi'i",
      "gold": 613268.97,
      "silver": 69820.37
    },
    "hanbali": {
      "label": "Hanbali",
      "gold": 613268.97,
      "silver": 69820.37
    }
  }
}