{
  "meta": {
    "updated_at": "2026-07-01T08:01:08.417Z",
    "currency": "EGP",
    "pegged_to_usd": false
  },
  "nisab": {
    "hanafi": {
      "label": "Hanafi",
      "gold": 534198.23,
      "silver": 54296.34
    },
    "maliki": {
      "label": "Maliki",
      "gold": 534198.23,
      "silver": 54296.34
    },
    "shafii": {
      "label": "Shafi'i",
      "gold": 534198.23,
      "silver": 54296.34
    },
    "hanbali": {
      "label": "Hanbali",
      "gold": 534198.23,
      "silver": 54296.34
    }
  }
}