{
  "meta": {
    "updated_at": "2026-05-29T02:53:28.672Z",
    "currency": "EGP",
    "pegged_to_usd": false
  },
  "nisab": {
    "hanafi": {
      "label": "Hanafi",
      "gold": 642978.55,
      "silver": 78072.62
    },
    "maliki": {
      "label": "Maliki",
      "gold": 642978.55,
      "silver": 75859.31
    },
    "shafii": {
      "label": "Shafi'i",
      "gold": 642978.55,
      "silver": 75859.31
    },
    "hanbali": {
      "label": "Hanbali",
      "gold": 642978.55,
      "silver": 75859.31
    }
  }
}