{
  "meta": {
    "updated_at": "2026-06-29T21:37:51.398Z",
    "currency": "EUR",
    "pegged_to_usd": false
  },
  "nisab": {
    "hanafi": {
      "label": "Hanafi",
      "gold": 9638.16,
      "silver": 978.93
    },
    "maliki": {
      "label": "Maliki",
      "gold": 9638.16,
      "silver": 978.93
    },
    "shafii": {
      "label": "Shafi'i",
      "gold": 9638.16,
      "silver": 978.93
    },
    "hanbali": {
      "label": "Hanbali",
      "gold": 9638.16,
      "silver": 978.93
    }
  }
}