{
  "meta": {
    "updated_at": "2026-06-03T03:45:10.041Z",
    "currency": "IDR",
    "pegged_to_usd": false
  },
  "nisab": {
    "hanafi": {
      "label": "Hanafi",
      "gold": 218897312,
      "silver": 26406510
    },
    "maliki": {
      "label": "Maliki",
      "gold": 218897312,
      "silver": 25657903
    },
    "shafii": {
      "label": "Shafi'i",
      "gold": 218897312,
      "silver": 25657903
    },
    "hanbali": {
      "label": "Hanbali",
      "gold": 218897312,
      "silver": 25657903
    }
  }
}