{
  "meta": {
    "updated_at": "2026-06-18T03:36:35.567Z",
    "currency": "INR",
    "pegged_to_usd": false
  },
  "nisab": {
    "hanafi": {
      "label": "Hanafi",
      "gold": 1113586.85,
      "silver": 128447.4
    },
    "maliki": {
      "label": "Maliki",
      "gold": 1113586.85,
      "silver": 124806
    },
    "shafii": {
      "label": "Shafi'i",
      "gold": 1113586.85,
      "silver": 124806
    },
    "hanbali": {
      "label": "Hanbali",
      "gold": 1113586.85,
      "silver": 124806
    }
  }
}