{
  "meta": {
    "updated_at": "2026-07-11T16:58:02.429Z",
    "currency": "INR",
    "pegged_to_usd": false
  },
  "nisab": {
    "hanafi": {
      "label": "Hanafi",
      "gold": 1073552.92,
      "silver": 109229.21
    },
    "maliki": {
      "label": "Maliki",
      "gold": 1073552.92,
      "silver": 109229.21
    },
    "shafii": {
      "label": "Shafi'i",
      "gold": 1073552.92,
      "silver": 109229.21
    },
    "hanbali": {
      "label": "Hanbali",
      "gold": 1073552.92,
      "silver": 109229.21
    }
  }
}