{
  "meta": {
    "updated_at": "2026-07-22T10:23:25.206Z",
    "currency": "INR",
    "pegged_to_usd": false
  },
  "nisab": {
    "hanafi": {
      "label": "Hanafi",
      "gold": 1085747.89,
      "silver": 109637.02
    },
    "maliki": {
      "label": "Maliki",
      "gold": 1085747.89,
      "silver": 109637.02
    },
    "shafii": {
      "label": "Shafi'i",
      "gold": 1085747.89,
      "silver": 109637.02
    },
    "hanbali": {
      "label": "Hanbali",
      "gold": 1085747.89,
      "silver": 109637.02
    }
  }
}