{
  "meta": {
    "updated_at": "2026-07-18T16:57:38.388Z",
    "currency": "INR",
    "pegged_to_usd": false
  },
  "nisab": {
    "hanafi": {
      "label": "Hanafi",
      "gold": 1061115.05,
      "silver": 103475.56
    },
    "maliki": {
      "label": "Maliki",
      "gold": 1061115.05,
      "silver": 103475.56
    },
    "shafii": {
      "label": "Shafi'i",
      "gold": 1061115.05,
      "silver": 103475.56
    },
    "hanbali": {
      "label": "Hanbali",
      "gold": 1061115.05,
      "silver": 103475.56
    }
  }
}