{
  "meta": {
    "updated_at": "2026-07-03T02:38:34.121Z",
    "currency": "JPY",
    "pegged_to_usd": false
  },
  "nisab": {
    "hanafi": {
      "label": "Hanafi",
      "gold": 1858638.03,
      "silver": 194191.08
    },
    "maliki": {
      "label": "Maliki",
      "gold": 1858638.03,
      "silver": 194191.08
    },
    "shafii": {
      "label": "Shafi'i",
      "gold": 1858638.03,
      "silver": 194191.08
    },
    "hanbali": {
      "label": "Hanbali",
      "gold": 1858638.03,
      "silver": 194191.08
    }
  }
}