{
  "meta": {
    "updated_at": "2026-06-18T08:28:58.925Z",
    "currency": "JPY",
    "pegged_to_usd": false
  },
  "nisab": {
    "hanafi": {
      "label": "Hanafi",
      "gold": 1877183.95,
      "silver": 215440.71
    },
    "maliki": {
      "label": "Maliki",
      "gold": 1877183.95,
      "silver": 209333.11
    },
    "shafii": {
      "label": "Shafi'i",
      "gold": 1877183.95,
      "silver": 209333.11
    },
    "hanbali": {
      "label": "Hanbali",
      "gold": 1877183.95,
      "silver": 209333.11
    }
  }
}