{
  "meta": {
    "updated_at": "2026-05-30T06:39:04.699Z",
    "currency": "KZT",
    "pegged_to_usd": false
  },
  "nisab": {
    "hanafi": {
      "label": "Hanafi",
      "gold": 5999064,
      "silver": 717096
    },
    "maliki": {
      "label": "Maliki",
      "gold": 5999064,
      "silver": 696767
    },
    "shafii": {
      "label": "Shafi'i",
      "gold": 5999064,
      "silver": 696767
    },
    "hanbali": {
      "label": "Hanbali",
      "gold": 5999064,
      "silver": 696767
    }
  }
}