{
  "meta": {
    "updated_at": "2026-06-27T17:10:02.314Z",
    "currency": "MAD",
    "pegged_to_usd": false
  },
  "nisab": {
    "hanafi": {
      "label": "Hanafi",
      "gold": 105126.61,
      "silver": 10645.61
    },
    "maliki": {
      "label": "Maliki",
      "gold": 105126.61,
      "silver": 10645.61
    },
    "shafii": {
      "label": "Shafi'i",
      "gold": 105126.61,
      "silver": 10645.61
    },
    "hanbali": {
      "label": "Hanbali",
      "gold": 105126.61,
      "silver": 10645.61
    }
  }
}