{
  "meta": {
    "updated_at": "2026-06-26T21:22:49.635Z",
    "currency": "NGN",
    "pegged_to_usd": false
  },
  "nisab": {
    "hanafi": {
      "label": "Hanafi",
      "gold": 15316500,
      "silver": 1551019
    },
    "maliki": {
      "label": "Maliki",
      "gold": 15316500,
      "silver": 1551019
    },
    "shafii": {
      "label": "Shafi'i",
      "gold": 15316500,
      "silver": 1551019
    },
    "hanbali": {
      "label": "Hanbali",
      "gold": 15316500,
      "silver": 1551019
    }
  }
}