{
  "meta": {
    "updated_at": "2026-06-28T21:06:18.642Z",
    "currency": "NGN",
    "pegged_to_usd": false
  },
  "nisab": {
    "hanafi": {
      "label": "Hanafi",
      "gold": 15407438,
      "silver": 1550904
    },
    "maliki": {
      "label": "Maliki",
      "gold": 15407438,
      "silver": 1550904
    },
    "shafii": {
      "label": "Shafi'i",
      "gold": 15407438,
      "silver": 1550904
    },
    "hanbali": {
      "label": "Hanbali",
      "gold": 15407438,
      "silver": 1550904
    }
  }
}