{
  "meta": {
    "updated_at": "2026-06-19T08:56:28.495Z",
    "currency": "NGN",
    "pegged_to_usd": false
  },
  "nisab": {
    "hanafi": {
      "label": "Hanafi",
      "gold": 15484016,
      "silver": 1743644
    },
    "maliki": {
      "label": "Maliki",
      "gold": 15484016,
      "silver": 1694213
    },
    "shafii": {
      "label": "Shafi'i",
      "gold": 15484016,
      "silver": 1694213
    },
    "hanbali": {
      "label": "Hanbali",
      "gold": 15484016,
      "silver": 1694213
    }
  }
}