{
  "meta": {
    "updated_at": "2026-06-26T17:48:05.128Z",
    "currency": "NOK",
    "pegged_to_usd": false
  },
  "nisab": {
    "hanafi": {
      "label": "Hanafi",
      "gold": 109735.26,
      "silver": 11163.59
    },
    "maliki": {
      "label": "Maliki",
      "gold": 109735.26,
      "silver": 11163.59
    },
    "shafii": {
      "label": "Shafi'i",
      "gold": 109735.26,
      "silver": 11163.59
    },
    "hanbali": {
      "label": "Hanbali",
      "gold": 109735.26,
      "silver": 11163.59
    }
  }
}