{
  "meta": {
    "updated_at": "2026-06-22T03:54:19.667Z",
    "currency": "OMR",
    "pegged_to_usd": true
  },
  "nisab": {
    "hanafi": {
      "label": "Hanafi",
      "gold": 4394.41,
      "silver": 496.53
    },
    "maliki": {
      "label": "Maliki",
      "gold": 4394.41,
      "silver": 482.45
    },
    "shafii": {
      "label": "Shafi'i",
      "gold": 4394.41,
      "silver": 482.45
    },
    "hanbali": {
      "label": "Hanbali",
      "gold": 4394.41,
      "silver": 482.45
    }
  }
}