{
  "meta": {
    "updated_at": "2026-07-22T13:49:02.945Z",
    "currency": "QAR",
    "pegged_to_usd": true
  },
  "nisab": {
    "hanafi": {
      "label": "Hanafi",
      "gold": 41271.11,
      "silver": 4192.54
    },
    "maliki": {
      "label": "Maliki",
      "gold": 41271.11,
      "silver": 4192.54
    },
    "shafii": {
      "label": "Shafi'i",
      "gold": 41271.11,
      "silver": 4192.54
    },
    "hanbali": {
      "label": "Hanbali",
      "gold": 41271.11,
      "silver": 4192.54
    }
  }
}