{
  "meta": {
    "updated_at": "2026-06-11T08:26:06.221Z",
    "currency": "SEK",
    "pegged_to_usd": false
  },
  "nisab": {
    "hanafi": {
      "label": "Hanafi",
      "gold": 106189.09,
      "silver": 12002.34
    },
    "maliki": {
      "label": "Maliki",
      "gold": 106189.09,
      "silver": 11662.08
    },
    "shafii": {
      "label": "Shafi'i",
      "gold": 106189.09,
      "silver": 11662.08
    },
    "hanbali": {
      "label": "Hanbali",
      "gold": 106189.09,
      "silver": 11662.08
    }
  }
}