{
  "meta": {
    "updated_at": "2026-06-25T10:40:16.588Z",
    "currency": "SGD",
    "pegged_to_usd": false
  },
  "nisab": {
    "hanafi": {
      "label": "Hanafi",
      "gold": 14140.06,
      "silver": 1427.32
    },
    "maliki": {
      "label": "Maliki",
      "gold": 14140.06,
      "silver": 1427.32
    },
    "shafii": {
      "label": "Shafi'i",
      "gold": 14140.06,
      "silver": 1427.32
    },
    "hanbali": {
      "label": "Hanbali",
      "gold": 14140.06,
      "silver": 1427.32
    }
  }
}