{
  "meta": {
    "updated_at": "2026-07-08T10:15:37.901Z",
    "currency": "TND",
    "pegged_to_usd": false
  },
  "nisab": {
    "hanafi": {
      "label": "Hanafi",
      "gold": 32584.7,
      "silver": 3295.36
    },
    "maliki": {
      "label": "Maliki",
      "gold": 32584.7,
      "silver": 3295.36
    },
    "shafii": {
      "label": "Shafi'i",
      "gold": 32584.7,
      "silver": 3295.36
    },
    "hanbali": {
      "label": "Hanbali",
      "gold": 32584.7,
      "silver": 3295.36
    }
  }
}