{
  "meta": {
    "updated_at": "2026-05-31T10:14:44.416Z",
    "currency": "TRY",
    "pegged_to_usd": false
  },
  "nisab": {
    "hanafi": {
      "label": "Hanafi",
      "gold": 568850.05,
      "silver": 67952.85
    },
    "maliki": {
      "label": "Maliki",
      "gold": 568850.05,
      "silver": 66026.43
    },
    "shafii": {
      "label": "Shafi'i",
      "gold": 568850.05,
      "silver": 66026.43
    },
    "hanbali": {
      "label": "Hanbali",
      "gold": 568850.05,
      "silver": 66026.43
    }
  }
}