{
  "meta": {
    "updated_at": "2026-06-03T19:49:18.768Z",
    "currency": "TRY",
    "pegged_to_usd": false
  },
  "nisab": {
    "hanafi": {
      "label": "Hanafi",
      "gold": 558364.59,
      "silver": 66321.33
    },
    "maliki": {
      "label": "Maliki",
      "gold": 558364.59,
      "silver": 64441.17
    },
    "shafii": {
      "label": "Shafi'i",
      "gold": 558364.59,
      "silver": 64441.17
    },
    "hanbali": {
      "label": "Hanbali",
      "gold": 558364.59,
      "silver": 64441.17
    }
  }
}