{
  "meta": {
    "updated_at": "2026-07-06T08:08:12.986Z",
    "currency": "USD",
    "pegged_to_usd": false
  },
  "nisab": {
    "hanafi": {
      "label": "Hanafi",
      "gold": 11372.69,
      "silver": 1195.09
    },
    "maliki": {
      "label": "Maliki",
      "gold": 11372.69,
      "silver": 1195.09
    },
    "shafii": {
      "label": "Shafi'i",
      "gold": 11372.69,
      "silver": 1195.09
    },
    "hanbali": {
      "label": "Hanbali",
      "gold": 11372.69,
      "silver": 1195.09
    }
  }
}