{
  "meta": {
    "updated_at": "2026-07-19T13:14:20.036Z",
    "currency": "USD",
    "pegged_to_usd": false
  },
  "nisab": {
    "hanafi": {
      "label": "Hanafi",
      "gold": 10979,
      "silver": 1069.3
    },
    "maliki": {
      "label": "Maliki",
      "gold": 10979,
      "silver": 1069.3
    },
    "shafii": {
      "label": "Shafi'i",
      "gold": 10979,
      "silver": 1069.3
    },
    "hanbali": {
      "label": "Hanbali",
      "gold": 10979,
      "silver": 1069.3
    }
  }
}