{
  "meta": {
    "updated_at": "2026-06-17T03:44:43.177Z",
    "currency": "USD",
    "pegged_to_usd": false
  },
  "nisab": {
    "hanafi": {
      "label": "Hanafi",
      "gold": 11842.38,
      "silver": 1380.84
    },
    "maliki": {
      "label": "Maliki",
      "gold": 11842.38,
      "silver": 1341.69
    },
    "shafii": {
      "label": "Shafi'i",
      "gold": 11842.38,
      "silver": 1341.69
    },
    "hanbali": {
      "label": "Hanbali",
      "gold": 11842.38,
      "silver": 1341.69
    }
  }
}