{
  "meta": {
    "updated_at": "2026-05-30T13:26:51.102Z",
    "currency": "ZAR",
    "pegged_to_usd": false
  },
  "nisab": {
    "hanafi": {
      "label": "Hanafi",
      "gold": 201494.71,
      "silver": 24073.21
    },
    "maliki": {
      "label": "Maliki",
      "gold": 201494.71,
      "silver": 23390.75
    },
    "shafii": {
      "label": "Shafi'i",
      "gold": 201494.71,
      "silver": 23390.75
    },
    "hanbali": {
      "label": "Hanbali",
      "gold": 201494.71,
      "silver": 23390.75
    }
  }
}