{
  "meta": {
    "updated_at": "2026-07-06T12:03:18.608Z",
    "currency": "ZAR",
    "pegged_to_usd": false
  },
  "nisab": {
    "hanafi": {
      "label": "Hanafi",
      "gold": 184388.51,
      "silver": 19302.31
    },
    "maliki": {
      "label": "Maliki",
      "gold": 184388.51,
      "silver": 19302.31
    },
    "shafii": {
      "label": "Shafi'i",
      "gold": 184388.51,
      "silver": 19302.31
    },
    "hanbali": {
      "label": "Hanbali",
      "gold": 184388.51,
      "silver": 19302.31
    }
  }
}