{
  "meta": {
    "timestamp": "2026-03-25T2044GMT",
    "updated_at": "2026-03-25T20:44:05.579Z",
    "timezone": "GMT",
    "base_currency": "USD",
    "currencies": [
      "USD",
      "GBP",
      "EUR",
      "CAD",
      "AUD",
      "JPY",
      "CHF",
      "CNY",
      "INR",
      "MYR",
      "IDR",
      "TRY",
      "ZAR",
      "SEK",
      "NOK",
      "SGD",
      "DKK"
    ],
    "disclaimer": "Nisab values are for informational purposes only. Consult a qualified scholar for your specific situation.",
    "source": "Nisab Al Zakat",
    "url": "nisab.tahababa.com",
    "data_source": "goldpricez.com",
    "github": "https://github.com/tahababa/nisab"
  },
  "prices": {
    "gold": {
      "per_troy_oz": 4505.83,
      "per_gram": 144.86569
    },
    "silver": {
      "per_troy_oz": 71.303,
      "per_gram": 2.292443
    }
  },
  "nisab": {
    "hanafi": {
      "label": "Hanafi",
      "note": "Based on 7.5 tola (87.48g) of gold or 52.5 tola (612.36g) of silver",
      "gold": {
        "grams": 87.48,
        "tola": 7.5,
        "values": {
          "USD": 12672.85,
          "GBP": 9477.39,
          "EUR": 10951.24,
          "CAD": 17423.9,
          "AUD": 18236.23,
          "JPY": 2014096.14,
          "CHF": 10014.97,
          "CNY": 87359.03,
          "INR": 1189347.03,
          "MYR": 50140.13,
          "IDR": 214057118.83,
          "TRY": 562015.58,
          "ZAR": 216729.82,
          "SEK": 118534.24,
          "NOK": 122988.75,
          "SGD": 16228.85,
          "DKK": 81818.46
        }
      },
      "silver": {
        "grams": 612.36,
        "tola": 52.5,
        "values": {
          "USD": 1403.8,
          "GBP": 1049.83,
          "EUR": 1213.09,
          "CAD": 1930.09,
          "AUD": 2020.07,
          "JPY": 223106,
          "CHF": 1109.38,
          "CNY": 9676.96,
          "INR": 131746.67,
          "MYR": 5554.14,
          "IDR": 23711592.48,
          "TRY": 62255.74,
          "ZAR": 24007.65,
          "SEK": 13130.31,
          "NOK": 13623.74,
          "SGD": 1797.71,
          "DKK": 9063.22
        }
      }
    },
    "maliki": {
      "label": "Maliki",
      "note": "Based on 85g of gold or 595g of silver",
      "gold": {
        "grams": 85,
        "values": {
          "USD": 12313.58,
          "GBP": 9208.71,
          "EUR": 10640.78,
          "CAD": 16929.95,
          "AUD": 17719.25,
          "JPY": 1956997.85,
          "CHF": 9731.06,
          "CNY": 84882.46,
          "INR": 1155629.83,
          "MYR": 48718.69,
          "IDR": 207988741.43,
          "TRY": 546082.81,
          "ZAR": 210585.68,
          "SEK": 115173.87,
          "NOK": 119502.1,
          "SGD": 15768.78,
          "DKK": 79498.96
        }
      },
      "silver": {
        "grams": 595,
        "values": {
          "USD": 1364,
          "GBP": 1020.07,
          "EUR": 1178.7,
          "CAD": 1875.37,
          "AUD": 1962.8,
          "JPY": 216781.09,
          "CHF": 1077.93,
          "CNY": 9402.62,
          "INR": 128011.74,
          "MYR": 5396.68,
          "IDR": 23039384.55,
          "TRY": 60490.83,
          "ZAR": 23327.05,
          "SEK": 12758.07,
          "NOK": 13237.52,
          "SGD": 1746.74,
          "DKK": 8806.28
        }
      }
    },
    "shafii": {
      "label": "Shafi'i",
      "note": "Based on 85g of gold or 595g of silver",
      "gold": {
        "grams": 85,
        "values": {
          "USD": 12313.58,
          "GBP": 9208.71,
          "EUR": 10640.78,
          "CAD": 16929.95,
          "AUD": 17719.25,
          "JPY": 1956997.85,
          "CHF": 9731.06,
          "CNY": 84882.46,
          "INR": 1155629.83,
          "MYR": 48718.69,
          "IDR": 207988741.43,
          "TRY": 546082.81,
          "ZAR": 210585.68,
          "SEK": 115173.87,
          "NOK": 119502.1,
          "SGD": 15768.78,
          "DKK": 79498.96
        }
      },
      "silver": {
        "grams": 595,
        "values": {
          "USD": 1364,
          "GBP": 1020.07,
          "EUR": 1178.7,
          "CAD": 1875.37,
          "AUD": 1962.8,
          "JPY": 216781.09,
          "CHF": 1077.93,
          "CNY": 9402.62,
          "INR": 128011.74,
          "MYR": 5396.68,
          "IDR": 23039384.55,
          "TRY": 60490.83,
          "ZAR": 23327.05,
          "SEK": 12758.07,
          "NOK": 13237.52,
          "SGD": 1746.74,
          "DKK": 8806.28
        }
      }
    },
    "hanbali": {
      "label": "Hanbali",
      "note": "Based on 85g of gold or 595g of silver",
      "gold": {
        "grams": 85,
        "values": {
          "USD": 12313.58,
          "GBP": 9208.71,
          "EUR": 10640.78,
          "CAD": 16929.95,
          "AUD": 17719.25,
          "JPY": 1956997.85,
          "CHF": 9731.06,
          "CNY": 84882.46,
          "INR": 1155629.83,
          "MYR": 48718.69,
          "IDR": 207988741.43,
          "TRY": 546082.81,
          "ZAR": 210585.68,
          "SEK": 115173.87,
          "NOK": 119502.1,
          "SGD": 15768.78,
          "DKK": 79498.96
        }
      },
      "silver": {
        "grams": 595,
        "values": {
          "USD": 1364,
          "GBP": 1020.07,
          "EUR": 1178.7,
          "CAD": 1875.37,
          "AUD": 1962.8,
          "JPY": 216781.09,
          "CHF": 1077.93,
          "CNY": 9402.62,
          "INR": 128011.74,
          "MYR": 5396.68,
          "IDR": 23039384.55,
          "TRY": 60490.83,
          "ZAR": 23327.05,
          "SEK": 12758.07,
          "NOK": 13237.52,
          "SGD": 1746.74,
          "DKK": 8806.28
        }
      }
    }
  }
}