{
  "meta": {
    "timestamp": "2026-05-15T1727GMT",
    "updated_at": "2026-05-15T17:27:37.922Z",
    "timezone": "GMT",
    "base_currency": "USD",
    "currencies": [
      "USD",
      "GBP",
      "EUR",
      "CAD",
      "AUD",
      "JPY",
      "CHF",
      "CNY",
      "INR",
      "MYR",
      "IDR",
      "TRY",
      "ZAR",
      "SEK",
      "NOK",
      "SGD",
      "DKK"
    ],
    "hijri": {
      "day": "28",
      "month_en": "Dhū al-Qaʿdah",
      "month_ar": "ذوالقعدة",
      "year": "1447",
      "formatted_en": "28 Dhū al-Qaʿdah 1447 AH",
      "formatted_ar": "28 ذوالقعدة 1447"
    },
    "disclaimer": "Nisab values are for informational purposes only. Consult a qualified scholar for your specific situation.",
    "source": "Nisab Al Zakat",
    "url": "nisab.tahababa.com",
    "data_source": "goldpricez.com",
    "github": "https://github.com/tahababa/nisab"
  },
  "prices": {
    "gold": {
      "per_troy_oz": 4560.83,
      "per_gram": 146.63398
    },
    "silver": {
      "per_troy_oz": 77.1047,
      "per_gram": 2.478972
    }
  },
  "nisab": {
    "hanafi": {
      "label": "Hanafi",
      "note": "Based on 85g of gold or 612.36g of silver",
      "gold": {
        "grams": 85,
        "values": {
          "USD": 12463.89,
          "GBP": 9330.72,
          "EUR": 10718.82,
          "CAD": 17145.32,
          "AUD": 17434.49,
          "JPY": 1976149.49,
          "CHF": 9801.35,
          "CNY": 84886.56,
          "INR": 1196159.36,
          "MYR": 49244.82,
          "IDR": 219227331.31,
          "TRY": 567667.79,
          "ZAR": 207665.83,
          "SEK": 117713.95,
          "NOK": 116245.7,
          "SGD": 15953.78,
          "DKK": 80100.42
        }
      },
      "silver": {
        "grams": 612.36,
        "tola": 52.5,
        "values": {
          "USD": 1518.02,
          "GBP": 1136.42,
          "EUR": 1305.48,
          "CAD": 2088.19,
          "AUD": 2123.41,
          "JPY": 240682.59,
          "CHF": 1193.74,
          "CNY": 10338.65,
          "INR": 145684.7,
          "MYR": 5997.71,
          "IDR": 26700511.72,
          "TRY": 69138.37,
          "ZAR": 25292.39,
          "SEK": 14336.82,
          "NOK": 14158,
          "SGD": 1943.07,
          "DKK": 9755.73
        }
      }
    },
    "maliki": {
      "label": "Maliki",
      "note": "Based on 85g of gold or 595g of silver",
      "gold": {
        "grams": 85,
        "values": {
          "USD": 12463.89,
          "GBP": 9330.72,
          "EUR": 10718.82,
          "CAD": 17145.32,
          "AUD": 17434.49,
          "JPY": 1976149.49,
          "CHF": 9801.35,
          "CNY": 84886.56,
          "INR": 1196159.36,
          "MYR": 49244.82,
          "IDR": 219227331.31,
          "TRY": 567667.79,
          "ZAR": 207665.83,
          "SEK": 117713.95,
          "NOK": 116245.7,
          "SGD": 15953.78,
          "DKK": 80100.42
        }
      },
      "silver": {
        "grams": 595,
        "values": {
          "USD": 1474.99,
          "GBP": 1104.21,
          "EUR": 1268.48,
          "CAD": 2028.99,
          "AUD": 2063.21,
          "JPY": 233859.4,
          "CHF": 1159.9,
          "CNY": 10045.56,
          "INR": 141554.63,
          "MYR": 5827.68,
          "IDR": 25943569.91,
          "TRY": 67178.34,
          "ZAR": 24575.37,
          "SEK": 13930.38,
          "NOK": 13756.63,
          "SGD": 1887.99,
          "DKK": 9479.16
        }
      }
    },
    "shafii": {
      "label": "Shafi'i",
      "note": "Based on 85g of gold or 595g of silver",
      "gold": {
        "grams": 85,
        "values": {
          "USD": 12463.89,
          "GBP": 9330.72,
          "EUR": 10718.82,
          "CAD": 17145.32,
          "AUD": 17434.49,
          "JPY": 1976149.49,
          "CHF": 9801.35,
          "CNY": 84886.56,
          "INR": 1196159.36,
          "MYR": 49244.82,
          "IDR": 219227331.31,
          "TRY": 567667.79,
          "ZAR": 207665.83,
          "SEK": 117713.95,
          "NOK": 116245.7,
          "SGD": 15953.78,
          "DKK": 80100.42
        }
      },
      "silver": {
        "grams": 595,
        "values": {
          "USD": 1474.99,
          "GBP": 1104.21,
          "EUR": 1268.48,
          "CAD": 2028.99,
          "AUD": 2063.21,
          "JPY": 233859.4,
          "CHF": 1159.9,
          "CNY": 10045.56,
          "INR": 141554.63,
          "MYR": 5827.68,
          "IDR": 25943569.91,
          "TRY": 67178.34,
          "ZAR": 24575.37,
          "SEK": 13930.38,
          "NOK": 13756.63,
          "SGD": 1887.99,
          "DKK": 9479.16
        }
      }
    },
    "hanbali": {
      "label": "Hanbali",
      "note": "Based on 85g of gold or 595g of silver",
      "gold": {
        "grams": 85,
        "values": {
          "USD": 12463.89,
          "GBP": 9330.72,
          "EUR": 10718.82,
          "CAD": 17145.32,
          "AUD": 17434.49,
          "JPY": 1976149.49,
          "CHF": 9801.35,
          "CNY": 84886.56,
          "INR": 1196159.36,
          "MYR": 49244.82,
          "IDR": 219227331.31,
          "TRY": 567667.79,
          "ZAR": 207665.83,
          "SEK": 117713.95,
          "NOK": 116245.7,
          "SGD": 15953.78,
          "DKK": 80100.42
        }
      },
      "silver": {
        "grams": 595,
        "values": {
          "USD": 1474.99,
          "GBP": 1104.21,
          "EUR": 1268.48,
          "CAD": 2028.99,
          "AUD": 2063.21,
          "JPY": 233859.4,
          "CHF": 1159.9,
          "CNY": 10045.56,
          "INR": 141554.63,
          "MYR": 5827.68,
          "IDR": 25943569.91,
          "TRY": 67178.34,
          "ZAR": 24575.37,
          "SEK": 13930.38,
          "NOK": 13756.63,
          "SGD": 1887.99,
          "DKK": 9479.16
        }
      }
    }
  }
}