{
  "meta": {
    "timestamp": "2026-04-21T0556GMT",
    "updated_at": "2026-04-21T05:56:43.804Z",
    "timezone": "GMT",
    "base_currency": "USD",
    "currencies": [
      "USD",
      "GBP",
      "EUR",
      "CAD",
      "AUD",
      "JPY",
      "CHF",
      "CNY",
      "INR",
      "MYR",
      "IDR",
      "TRY",
      "ZAR",
      "SEK",
      "NOK",
      "SGD",
      "DKK"
    ],
    "hijri": {
      "day": "4",
      "month_en": "Dhū al-Qaʿdah",
      "month_ar": "ذوالقعدة",
      "year": "1447",
      "formatted_en": "4 Dhū al-Qaʿdah 1447 AH",
      "formatted_ar": "4 ذوالقعدة 1447"
    },
    "disclaimer": "Nisab values are for informational purposes only. Consult a qualified scholar for your specific situation.",
    "source": "Nisab Al Zakat",
    "url": "nisab.tahababa.com",
    "data_source": "goldpricez.com",
    "github": "https://github.com/tahababa/nisab"
  },
  "prices": {
    "gold": {
      "per_troy_oz": 4784.905,
      "per_gram": 153.838153
    },
    "silver": {
      "per_troy_oz": 78.9905,
      "per_gram": 2.539602
    }
  },
  "nisab": {
    "hanafi": {
      "label": "Hanafi",
      "note": "Based on 85g of gold or 612.36g of silver",
      "gold": {
        "grams": 85,
        "values": {
          "USD": 13076.24,
          "GBP": 9678.77,
          "EUR": 11119.25,
          "CAD": 17907.91,
          "AUD": 18271.43,
          "JPY": 2077945.78,
          "CHF": 10217.51,
          "CNY": 89149.9,
          "INR": 1217005.94,
          "MYR": 51683.85,
          "IDR": 223982966.43,
          "TRY": 586848.71,
          "ZAR": 213795.27,
          "SEK": 119737.85,
          "NOK": 122028.81,
          "SGD": 16625.14,
          "DKK": 83098.22
        }
      },
      "silver": {
        "grams": 612.36,
        "tola": 52.5,
        "values": {
          "USD": 1555.15,
          "GBP": 1151.09,
          "EUR": 1322.41,
          "CAD": 2129.78,
          "AUD": 2173.01,
          "JPY": 247128.99,
          "CHF": 1215.16,
          "CNY": 10602.55,
          "INR": 144737.87,
          "MYR": 6146.73,
          "IDR": 26638176.01,
          "TRY": 69793.61,
          "ZAR": 25426.56,
          "SEK": 14240.36,
          "NOK": 14512.82,
          "SGD": 1977.22,
          "DKK": 9882.83
        }
      }
    },
    "maliki": {
      "label": "Maliki",
      "note": "Based on 85g of gold or 595g of silver",
      "gold": {
        "grams": 85,
        "values": {
          "USD": 13076.24,
          "GBP": 9678.77,
          "EUR": 11119.25,
          "CAD": 17907.91,
          "AUD": 18271.43,
          "JPY": 2077945.78,
          "CHF": 10217.51,
          "CNY": 89149.9,
          "INR": 1217005.94,
          "MYR": 51683.85,
          "IDR": 223982966.43,
          "TRY": 586848.71,
          "ZAR": 213795.27,
          "SEK": 119737.85,
          "NOK": 122028.81,
          "SGD": 16625.14,
          "DKK": 83098.22
        }
      },
      "silver": {
        "grams": 595,
        "values": {
          "USD": 1511.06,
          "GBP": 1118.46,
          "EUR": 1284.92,
          "CAD": 2069.4,
          "AUD": 2111.41,
          "JPY": 240123.05,
          "CHF": 1180.71,
          "CNY": 10301.98,
          "INR": 140634.65,
          "MYR": 5972.48,
          "IDR": 25883001.38,
          "TRY": 67815,
          "ZAR": 24705.73,
          "SEK": 13836.65,
          "NOK": 14101.39,
          "SGD": 1921.17,
          "DKK": 9602.66
        }
      }
    },
    "shafii": {
      "label": "Shafi'i",
      "note": "Based on 85g of gold or 595g of silver",
      "gold": {
        "grams": 85,
        "values": {
          "USD": 13076.24,
          "GBP": 9678.77,
          "EUR": 11119.25,
          "CAD": 17907.91,
          "AUD": 18271.43,
          "JPY": 2077945.78,
          "CHF": 10217.51,
          "CNY": 89149.9,
          "INR": 1217005.94,
          "MYR": 51683.85,
          "IDR": 223982966.43,
          "TRY": 586848.71,
          "ZAR": 213795.27,
          "SEK": 119737.85,
          "NOK": 122028.81,
          "SGD": 16625.14,
          "DKK": 83098.22
        }
      },
      "silver": {
        "grams": 595,
        "values": {
          "USD": 1511.06,
          "GBP": 1118.46,
          "EUR": 1284.92,
          "CAD": 2069.4,
          "AUD": 2111.41,
          "JPY": 240123.05,
          "CHF": 1180.71,
          "CNY": 10301.98,
          "INR": 140634.65,
          "MYR": 5972.48,
          "IDR": 25883001.38,
          "TRY": 67815,
          "ZAR": 24705.73,
          "SEK": 13836.65,
          "NOK": 14101.39,
          "SGD": 1921.17,
          "DKK": 9602.66
        }
      }
    },
    "hanbali": {
      "label": "Hanbali",
      "note": "Based on 85g of gold or 595g of silver",
      "gold": {
        "grams": 85,
        "values": {
          "USD": 13076.24,
          "GBP": 9678.77,
          "EUR": 11119.25,
          "CAD": 17907.91,
          "AUD": 18271.43,
          "JPY": 2077945.78,
          "CHF": 10217.51,
          "CNY": 89149.9,
          "INR": 1217005.94,
          "MYR": 51683.85,
          "IDR": 223982966.43,
          "TRY": 586848.71,
          "ZAR": 213795.27,
          "SEK": 119737.85,
          "NOK": 122028.81,
          "SGD": 16625.14,
          "DKK": 83098.22
        }
      },
      "silver": {
        "grams": 595,
        "values": {
          "USD": 1511.06,
          "GBP": 1118.46,
          "EUR": 1284.92,
          "CAD": 2069.4,
          "AUD": 2111.41,
          "JPY": 240123.05,
          "CHF": 1180.71,
          "CNY": 10301.98,
          "INR": 140634.65,
          "MYR": 5972.48,
          "IDR": 25883001.38,
          "TRY": 67815,
          "ZAR": 24705.73,
          "SEK": 13836.65,
          "NOK": 14101.39,
          "SGD": 1921.17,
          "DKK": 9602.66
        }
      }
    }
  }
}